KPU/Kalacell.py
KPU/__init__.py
kpu-1.1.2.dist-info/METADATA
kpu-1.1.2.dist-info/WHEEL
kpu-1.1.2.dist-info/top_level.txt
kpu-1.1.2.dist-info/RECORD
