Metadata-Version: 2.4
Name: KPU
Version: 1.1.2
Summary: KPU Quantum Computing Chip - AI & Cybersecurity Innovation
Author: N V R K SAI KAMESH YADAVALLI 
Author-email: saikamesh.y@gmail.com
Classifier: Programming Language :: Python :: 3
Classifier: Operating System :: OS Independent
Requires-Python: >=3.7
Requires-Dist: tensorflow
Requires-Dist: numpy
Requires-Dist: rich
Dynamic: author
Dynamic: author-email
Dynamic: classifier
Dynamic: description
Dynamic: description-content-type
Dynamic: requires-dist
Dynamic: requires-python
Dynamic: summary
